vipy/__init__.py
vipy/activity.py
vipy/annotation.py
vipy/batch.py
vipy/calibration.py
vipy/dataset.py
vipy/downloader.py
vipy/flow.py
vipy/geometry.py
vipy/globals.py
vipy/image.py
vipy/linalg.py
vipy/math.py
vipy/metrics.py
vipy/noise.py
vipy/object.py
vipy/parallel.py
vipy/pyramid.py
vipy/show.py
vipy/torch.py
vipy/util.py
vipy/version.py
vipy/video.py
vipy/visualize.py
vipy/data/__init__.py
vipy/data/_mnist.py
vipy/data/abo.py
vipy/data/activitynet.py
vipy/data/aflw.py
vipy/data/ava.py
vipy/data/caltech101.py
vipy/data/caltech256.py
vipy/data/cap.py
vipy/data/casia.py
vipy/data/cc12m.py
vipy/data/celebA.py
vipy/data/charades.py
vipy/data/cifar.py
vipy/data/coco.py
vipy/data/coil100.py
vipy/data/compcars.py
vipy/data/d2d.py
vipy/data/deepfashion.py
vipy/data/emnist.py
vipy/data/ethzshapes.py
vipy/data/eurosat.py
vipy/data/facescrub.py
vipy/data/fddb.py
vipy/data/food101.py
vipy/data/food2k.py
vipy/data/hf.py
vipy/data/hmdb.py
vipy/data/imagenet.py
vipy/data/imdb_wiki.py
vipy/data/inaturalist.py
vipy/data/kinetics.py
vipy/data/kitti.py
vipy/data/kthactions.py
vipy/data/lfw.py
vipy/data/lvis.py
vipy/data/megaface.py
vipy/data/meva.py
vipy/data/mit67.py
vipy/data/mmcommons.py
vipy/data/mmid.py
vipy/data/mnist.py
vipy/data/momentsintime.py
vipy/data/msceleb.py
vipy/data/objectnet.py
vipy/data/openimages.py
vipy/data/oxford_flowers_102.py
vipy/data/pip.py
vipy/data/places.py
vipy/data/stanford_cars.py
vipy/data/stanford_dogs.py
vipy/data/tiny_virat.py
vipy/data/ucf101.py
vipy/data/vggface.py
vipy/data/vggface2.py
vipy/data/visualgenome.py
vipy/data/widerface.py
vipy/data/youtubeBB.py
vipy/data/youtubefaces.py
vipy/gui/__init__.py
vipy/gui/using_matplotlib.py
vipy-1.16.3.dist-info/licenses/LICENSE
vipy-1.16.3.dist-info/METADATA
vipy-1.16.3.dist-info/WHEEL
vipy-1.16.3.dist-info/top_level.txt
vipy-1.16.3.dist-info/RECORD
