Metadata-Version: 2.4
Name: vipy
Version: 1.16.3
Summary: Python Tools for Visual Dataset Transformation
Home-page: https://github.com/visym/vipy
Download-URL: https://github.com/visym/vipy/archive/1.16.3.tar.gz
Author: Visym Labs
Author-email: info@visym.com
Keywords: computer vision machine learning ML CV privacy video image
Classifier: Programming Language :: Python :: 3
Classifier: Operating System :: OS Independent
Classifier: License :: OSI Approved :: MIT License
License-File: LICENSE
Requires-Dist: numpy
Requires-Dist: matplotlib
Requires-Dist: pillow
Requires-Dist: ffmpeg-python
Provides-Extra: fast
Requires-Dist: ujson; extra == "fast"
Requires-Dist: numba; extra == "fast"
Provides-Extra: all
Requires-Dist: scikit-build; extra == "all"
Requires-Dist: scipy; extra == "all"
Requires-Dist: opencv-python; extra == "all"
Requires-Dist: torch; extra == "all"
Requires-Dist: ipython; extra == "all"
Requires-Dist: scikit-learn; extra == "all"
Requires-Dist: boto3; extra == "all"
Requires-Dist: yt-dlp; extra == "all"
Requires-Dist: dask; extra == "all"
Requires-Dist: distributed; extra == "all"
Requires-Dist: h5py; extra == "all"
Requires-Dist: nltk; extra == "all"
Requires-Dist: bs4; extra == "all"
Requires-Dist: pyyaml; extra == "all"
Requires-Dist: pytest; extra == "all"
Requires-Dist: paramiko; extra == "all"
Requires-Dist: scp; extra == "all"
Requires-Dist: ujson; extra == "all"
Requires-Dist: pdoc3; extra == "all"
Requires-Dist: dill; extra == "all"
Requires-Dist: pillow; extra == "all"
Requires-Dist: numpy; extra == "all"
Requires-Dist: matplotlib; extra == "all"
Requires-Dist: ffmpeg-python; extra == "all"
Requires-Dist: heyvi; extra == "all"
Requires-Dist: datasets; extra == "all"
Requires-Dist: plenoptic; extra == "all"
Requires-Dist: dill; extra == "all"
Provides-Extra: complete
Requires-Dist: scikit-build; extra == "complete"
Requires-Dist: scipy; extra == "complete"
Requires-Dist: opencv-python; extra == "complete"
Requires-Dist: torch; extra == "complete"
Requires-Dist: ipython; extra == "complete"
Requires-Dist: scikit-learn; extra == "complete"
Requires-Dist: boto3; extra == "complete"
Requires-Dist: yt-dlp; extra == "complete"
Requires-Dist: dask; extra == "complete"
Requires-Dist: distributed; extra == "complete"
Requires-Dist: h5py; extra == "complete"
Requires-Dist: nltk; extra == "complete"
Requires-Dist: bs4; extra == "complete"
Requires-Dist: pyyaml; extra == "complete"
Requires-Dist: pytest; extra == "complete"
Requires-Dist: paramiko; extra == "complete"
Requires-Dist: scp; extra == "complete"
Requires-Dist: ujson; extra == "complete"
Requires-Dist: numba; extra == "complete"
Requires-Dist: pdoc3; extra == "complete"
Requires-Dist: dill; extra == "complete"
Requires-Dist: pillow; extra == "complete"
Requires-Dist: numpy; extra == "complete"
Requires-Dist: matplotlib; extra == "complete"
Requires-Dist: ffmpeg-python; extra == "complete"
Requires-Dist: heyvi; extra == "complete"
Requires-Dist: datasets; extra == "complete"
Requires-Dist: plenoptic; extra == "complete"
Requires-Dist: dill; extra == "complete"
Dynamic: author
Dynamic: author-email
Dynamic: classifier
Dynamic: description
Dynamic: description-content-type
Dynamic: download-url
Dynamic: home-page
Dynamic: keywords
Dynamic: license-file
Dynamic: provides-extra
Dynamic: requires-dist
Dynamic: summary
